{
  "a_comp_cor_00": {
    "CumulativeVarianceExplained": 0.0541920899,
    "Mask": "combined",
    "Method": "aCompCor",
    "Retained": true,
    "SingularValue": 139.0530030583,
    "VarianceExplained": 0.0541920899
  },
  "a_comp_cor_01": {
    "CumulativeVarianceExplained": 0.1020654177,
    "Mask": "combined",
    "Method": "aCompCor",
    "Retained": true,
    "SingularValue": 130.6950779159,
    "VarianceExplained": 0.0478733279
  },
  "a_comp_cor_02": {
    "CumulativeVarianceExplained": 0.1292097071,
    "Mask": "combined",
    "Method": "aCompCor",
    "Retained": true,
    "SingularValue": 98.4128164377,
    "VarianceExplained": 0.0271442893
  },
  "a_comp_cor_03": {
    "CumulativeVarianceExplained": 0.1527802725,
    "Mask": "combined",
    "Method": "aCompCor",
    "Retained": true,
    "SingularValue": 91.7059307239,
    "VarianceExplained": 0.0235705654
  },
  "a_comp_cor_04": {
    "CumulativeVarianceExplained": 0.1751361808,
    "Mask": "combined",
    "Method": "aCompCor",
    "Retained": true,
    "SingularValue": 89.3117466496,
    "VarianceExplained": 0.0223559083
  },
  "a_comp_cor_05": {
    "CumulativeVarianceExplained": 0.1948913315,
    "Mask": "combined",
    "Method": "aCompCor",
    "Retained": true,
    "SingularValue": 83.9561658454,
    "VarianceExplained": 0.0197551507
  },
  "a_comp_cor_06": {
    "CumulativeVarianceExplained": 0.2115298504,
    "Mask": "combined",
    "Method": "aCompCor",
    "Retained": true,
    "SingularValue": 77.0494874499,
    "VarianceExplained": 0.0166385188
  },
  "a_comp_cor_07": {
    "CumulativeVarianceExplained": 0.2265107317,
    "Mask": "combined",
    "Method": "aCompCor",
    "Retained": true,
    "SingularValue": 73.1107273309,
    "VarianceExplained": 0.0149808813
  },
  "a_comp_cor_08": {
    "CumulativeVarianceExplained": 0.2410361205,
    "Mask": "combined",
    "Method": "aCompCor",
    "Retained": true,
    "SingularValue": 71.990685056,
    "VarianceExplained": 0.0145253888
  },
  "a_comp_cor_09": {
    "CumulativeVarianceExplained": 0.2552293876,
    "Mask": "combined",
    "Method": "aCompCor",
    "Retained": true,
    "SingularValue": 71.1628956074,
    "VarianceExplained": 0.0141932671
  },
  "a_comp_cor_10": {
    "CumulativeVarianceExplained": 0.2687324552,
    "Mask": "combined",
    "Method": "aCompCor",
    "Retained": true,
    "SingularValue": 69.4110545634,
    "VarianceExplained": 0.0135030675
  },
  "a_comp_cor_11": {
    "CumulativeVarianceExplained": 0.281988118,
    "Mask": "combined",
    "Method": "aCompCor",
    "Retained": true,
    "SingularValue": 68.7722363419,
    "VarianceExplained": 0.0132556628
  },
  "a_comp_cor_12": {
    "CumulativeVarianceExplained": 0.2948794532,
    "Mask": "combined",
    "Method": "aCompCor",
    "Retained": true,
    "SingularValue": 67.8205602626,
    "VarianceExplained": 0.0128913352
  },
  "a_comp_cor_13": {
    "CumulativeVarianceExplained": 0.3076464356,
    "Mask": "combined",
    "Method": "aCompCor",
    "Retained": true,
    "SingularValue": 67.4926613398,
    "VarianceExplained": 0.0127669824
  },
  "a_comp_cor_14": {
    "CumulativeVarianceExplained": 0.3201799025,
    "Mask": "combined",
    "Method": "aCompCor",
    "Retained": true,
    "SingularValue": 66.8725727299,
    "VarianceExplained": 0.0125334669
  },
  "a_comp_cor_15": {
    "CumulativeVarianceExplained": 0.3326312201,
    "Mask": "combined",
    "Method": "aCompCor",
    "Retained": true,
    "SingularValue": 66.6530578894,
    "VarianceExplained": 0.0124513176
  },
  "a_comp_cor_16": {
    "CumulativeVarianceExplained": 0.3446979048,
    "Mask": "combined",
    "Method": "aCompCor",
    "Retained": true,
    "SingularValue": 65.6154944101,
    "VarianceExplained": 0.0120666847
  },
  "a_comp_cor_17": {
    "CumulativeVarianceExplained": 0.3565485813,
    "Mask": "combined",
    "Method": "aCompCor",
    "Retained": true,
    "SingularValue": 65.0255439913,
    "VarianceExplained": 0.0118506765
  },
  "a_comp_cor_18": {
    "CumulativeVarianceExplained": 0.3681647142,
    "Mask": "combined",
    "Method": "aCompCor",
    "Retained": true,
    "SingularValue": 64.3788491004,
    "VarianceExplained": 0.0116161329
  },
  "a_comp_cor_19": {
    "CumulativeVarianceExplained": 0.3797350956,
    "Mask": "combined",
    "Method": "aCompCor",
    "Retained": true,
    "SingularValue": 64.2519421583,
    "VarianceExplained": 0.0115703814
  },
  "a_comp_cor_20": {
    "CumulativeVarianceExplained": 0.3910817301,
    "Mask": "combined",
    "Method": "aCompCor",
    "Retained": true,
    "SingularValue": 63.6276606394,
    "VarianceExplained": 0.0113466345
  },
  "a_comp_cor_21": {
    "CumulativeVarianceExplained": 0.4023173454,
    "Mask": "combined",
    "Method": "aCompCor",
    "Retained": true,
    "SingularValue": 63.3156185201,
    "VarianceExplained": 0.0112356153
  },
  "a_comp_cor_22": {
    "CumulativeVarianceExplained": 0.4135031549,
    "Mask": "combined",
    "Method": "aCompCor",
    "Retained": true,
    "SingularValue": 63.1751282339,
    "VarianceExplained": 0.0111858095
  },
  "a_comp_cor_23": {
    "CumulativeVarianceExplained": 0.4246485933,
    "Mask": "combined",
    "Method": "aCompCor",
    "Retained": true,
    "SingularValue": 63.0610213603,
    "VarianceExplained": 0.0111454384
  },
  "a_comp_cor_24": {
    "CumulativeVarianceExplained": 0.4356093681,
    "Mask": "combined",
    "Method": "aCompCor",
    "Retained": true,
    "SingularValue": 62.5364250452,
    "VarianceExplained": 0.0109607748
  },
  "a_comp_cor_25": {
    "CumulativeVarianceExplained": 0.4464581234,
    "Mask": "combined",
    "Method": "aCompCor",
    "Retained": true,
    "SingularValue": 62.2160419535,
    "VarianceExplained": 0.0108487553
  },
  "a_comp_cor_26": {
    "CumulativeVarianceExplained": 0.4572430764,
    "Mask": "combined",
    "Method": "aCompCor",
    "Retained": true,
    "SingularValue": 62.0328238848,
    "VarianceExplained": 0.010784953
  },
  "a_comp_cor_27": {
    "CumulativeVarianceExplained": 0.4677959428,
    "Mask": "combined",
    "Method": "aCompCor",
    "Retained": true,
    "SingularValue": 61.3617366956,
    "VarianceExplained": 0.0105528664
  },
  "a_comp_cor_28": {
    "CumulativeVarianceExplained": 0.4782855885,
    "Mask": "combined",
    "Method": "aCompCor",
    "Retained": true,
    "SingularValue": 61.1776561032,
    "VarianceExplained": 0.0104896458
  },
  "a_comp_cor_29": {
    "CumulativeVarianceExplained": 0.4886931698,
    "Mask": "combined",
    "Method": "aCompCor",
    "Retained": true,
    "SingularValue": 60.937878235,
    "VarianceExplained": 0.0104075813
  },
  "a_comp_cor_30": {
    "CumulativeVarianceExplained": 0.4990081515,
    "Mask": "combined",
    "Method": "aCompCor",
    "Retained": true,
    "SingularValue": 60.6661804671,
    "VarianceExplained": 0.0103149816
  },
  "a_comp_cor_31": {
    "CumulativeVarianceExplained": 0.5091815771,
    "Mask": "combined",
    "Method": "aCompCor",
    "Retained": true,
    "SingularValue": 60.2484710686,
    "VarianceExplained": 0.0101734256
  },
  "aroma_motion_1": {
    "CSFFraction": 0.01,
    "EdgeFraction": 0.52,
    "HighFrequencyContent": 0.05,
    "MaximumRpCorrelation": 0.88,
    "Method": {
      "Name": "ICA-AROMA",
      "Version": "0.4.5"
    },
    "ModelVarianceExplained": 0.0691237162,
    "MotionNoise": true,
    "TotalVarianceExplained": 0.0498679123
  },
  "aroma_motion_10": {
    "CSFFraction": 0.08,
    "EdgeFraction": 0.51,
    "HighFrequencyContent": 0.47,
    "MaximumRpCorrelation": 0.35,
    "Method": {
      "Name": "ICA-AROMA",
      "Version": "0.4.5"
    },
    "ModelVarianceExplained": 0.0515800611,
    "MotionNoise": true,
    "TotalVarianceExplained": 0.0372113958
  },
  "aroma_motion_11": {
    "CSFFraction": 0.0,
    "EdgeFraction": 0.53,
    "HighFrequencyContent": 0.14,
    "MaximumRpCorrelation": 0.5,
    "Method": {
      "Name": "ICA-AROMA",
      "Version": "0.4.5"
    },
    "ModelVarianceExplained": 0.0476336751,
    "MotionNoise": false,
    "TotalVarianceExplained": 0.0343643552
  },
  "aroma_motion_12": {
    "CSFFraction": 0.08,
    "EdgeFraction": 0.47,
    "HighFrequencyContent": 0.49,
    "MaximumRpCorrelation": 0.46,
    "Method": {
      "Name": "ICA-AROMA",
      "Version": "0.4.5"
    },
    "ModelVarianceExplained": 0.0456223379,
    "MotionNoise": true,
    "TotalVarianceExplained": 0.0329133164
  },
  "aroma_motion_13": {
    "CSFFraction": 0.01,
    "EdgeFraction": 0.44,
    "HighFrequencyContent": 0.12,
    "MaximumRpCorrelation": 0.46,
    "Method": {
      "Name": "ICA-AROMA",
      "Version": "0.4.5"
    },
    "ModelVarianceExplained": 0.0448452398,
    "MotionNoise": false,
    "TotalVarianceExplained": 0.0323526947
  },
  "aroma_motion_14": {
    "CSFFraction": 0.01,
    "EdgeFraction": 0.94,
    "HighFrequencyContent": 0.33,
    "MaximumRpCorrelation": 0.55,
    "Method": {
      "Name": "ICA-AROMA",
      "Version": "0.4.5"
    },
    "ModelVarianceExplained": 0.0429011533,
    "MotionNoise": true,
    "TotalVarianceExplained": 0.0309501726
  },
  "aroma_motion_15": {
    "CSFFraction": 0.13,
    "EdgeFraction": 0.57,
    "HighFrequencyContent": 0.35,
    "MaximumRpCorrelation": 0.32,
    "Method": {
      "Name": "ICA-AROMA",
      "Version": "0.4.5"
    },
    "ModelVarianceExplained": 0.0405234639,
    "MotionNoise": true,
    "TotalVarianceExplained": 0.0292348365
  },
  "aroma_motion_16": {
    "CSFFraction": 0.01,
    "EdgeFraction": 0.57,
    "HighFrequencyContent": 0.07,
    "MaximumRpCorrelation": 0.53,
    "Method": {
      "Name": "ICA-AROMA",
      "Version": "0.4.5"
    },
    "ModelVarianceExplained": 0.0400016307,
    "MotionNoise": false,
    "TotalVarianceExplained": 0.0288583705
  },
  "aroma_motion_17": {
    "CSFFraction": 0.01,
    "EdgeFraction": 0.75,
    "HighFrequencyContent": 0.41,
    "MaximumRpCorrelation": 0.29,
    "Method": {
      "Name": "ICA-AROMA",
      "Version": "0.4.5"
    },
    "ModelVarianceExplained": 0.0399775752,
    "MotionNoise": true,
    "TotalVarianceExplained": 0.0288410162
  },
  "aroma_motion_18": {
    "CSFFraction": 0.05,
    "EdgeFraction": 0.51,
    "HighFrequencyContent": 0.16,
    "MaximumRpCorrelation": 0.27,
    "Method": {
      "Name": "ICA-AROMA",
      "Version": "0.4.5"
    },
    "ModelVarianceExplained": 0.0348430647,
    "MotionNoise": false,
    "TotalVarianceExplained": 0.025136827
  },
  "aroma_motion_19": {
    "CSFFraction": 0.04,
    "EdgeFraction": 0.52,
    "HighFrequencyContent": 0.22,
    "MaximumRpCorrelation": 0.33,
    "Method": {
      "Name": "ICA-AROMA",
      "Version": "0.4.5"
    },
    "ModelVarianceExplained": 0.0348103204,
    "MotionNoise": false,
    "TotalVarianceExplained": 0.0251132042
  },
  "aroma_motion_2": {
    "CSFFraction": 0.01,
    "EdgeFraction": 0.59,
    "HighFrequencyContent": 0.09,
    "MaximumRpCorrelation": 0.89,
    "Method": {
      "Name": "ICA-AROMA",
      "Version": "0.4.5"
    },
    "ModelVarianceExplained": 0.0676608643,
    "MotionNoise": true,
    "TotalVarianceExplained": 0.0488125672
  },
  "aroma_motion_20": {
    "CSFFraction": 0.04,
    "EdgeFraction": 0.46,
    "HighFrequencyContent": 0.22,
    "MaximumRpCorrelation": 0.43,
    "Method": {
      "Name": "ICA-AROMA",
      "Version": "0.4.5"
    },
    "ModelVarianceExplained": 0.0331005665,
    "MotionNoise": false,
    "TotalVarianceExplained": 0.0238797368
  },
  "aroma_motion_3": {
    "CSFFraction": 0.09,
    "EdgeFraction": 0.48,
    "HighFrequencyContent": 0.41,
    "MaximumRpCorrelation": 0.35,
    "Method": {
      "Name": "ICA-AROMA",
      "Version": "0.4.5"
    },
    "ModelVarianceExplained": 0.0668778176,
    "MotionNoise": true,
    "TotalVarianceExplained": 0.048247654
  },
  "aroma_motion_4": {
    "CSFFraction": 0.0,
    "EdgeFraction": 0.48,
    "HighFrequencyContent": 0.03,
    "MaximumRpCorrelation": 0.44,
    "Method": {
      "Name": "ICA-AROMA",
      "Version": "0.4.5"
    },
    "ModelVarianceExplained": 0.0619658271,
    "MotionNoise": false,
    "TotalVarianceExplained": 0.0447039974
  },
  "aroma_motion_5": {
    "CSFFraction": 0.08,
    "EdgeFraction": 0.51,
    "HighFrequencyContent": 0.39,
    "MaximumRpCorrelation": 0.34,
    "Method": {
      "Name": "ICA-AROMA",
      "Version": "0.4.5"
    },
    "ModelVarianceExplained": 0.0579758372,
    "MotionNoise": true,
    "TotalVarianceExplained": 0.0418254996
  },
  "aroma_motion_6": {
    "CSFFraction": 0.16,
    "EdgeFraction": 0.66,
    "HighFrequencyContent": 0.35,
    "MaximumRpCorrelation": 0.23,
    "Method": {
      "Name": "ICA-AROMA",
      "Version": "0.4.5"
    },
    "ModelVarianceExplained": 0.0571284713,
    "MotionNoise": true,
    "TotalVarianceExplained": 0.0412141846
  },
  "aroma_motion_7": {
    "CSFFraction": 0.01,
    "EdgeFraction": 0.27,
    "HighFrequencyContent": 0.03,
    "MaximumRpCorrelation": 0.39,
    "Method": {
      "Name": "ICA-AROMA",
      "Version": "0.4.5"
    },
    "ModelVarianceExplained": 0.0553961304,
    "MotionNoise": false,
    "TotalVarianceExplained": 0.0399644221
  },
  "aroma_motion_8": {
    "CSFFraction": 0.0,
    "EdgeFraction": 0.43,
    "HighFrequencyContent": 0.07,
    "MaximumRpCorrelation": 0.89,
    "Method": {
      "Name": "ICA-AROMA",
      "Version": "0.4.5"
    },
    "ModelVarianceExplained": 0.0542624108,
    "MotionNoise": false,
    "TotalVarianceExplained": 0.0391465229
  },
  "aroma_motion_9": {
    "CSFFraction": 0.02,
    "EdgeFraction": 0.5,
    "HighFrequencyContent": 0.2,
    "MaximumRpCorrelation": 0.82,
    "Method": {
      "Name": "ICA-AROMA",
      "Version": "0.4.5"
    },
    "ModelVarianceExplained": 0.0537698362,
    "MotionNoise": true,
    "TotalVarianceExplained": 0.038791165
  },
  "c_comp_cor_00": {
    "CumulativeVarianceExplained": 0.1587262344,
    "Mask": "CSF",
    "Method": "aCompCor",
    "Retained": true,
    "SingularValue": 97.588800915,
    "VarianceExplained": 0.1587262344
  },
  "c_comp_cor_01": {
    "CumulativeVarianceExplained": 0.3036038976,
    "Mask": "CSF",
    "Method": "aCompCor",
    "Retained": true,
    "SingularValue": 93.2344345802,
    "VarianceExplained": 0.1448776632
  },
  "c_comp_cor_02": {
    "CumulativeVarianceExplained": 0.3601147955,
    "Mask": "CSF",
    "Method": "aCompCor",
    "Retained": true,
    "SingularValue": 58.2293214205,
    "VarianceExplained": 0.0565108979
  },
  "c_comp_cor_03": {
    "CumulativeVarianceExplained": 0.4002810474,
    "Mask": "CSF",
    "Method": "aCompCor",
    "Retained": true,
    "SingularValue": 49.0914973991,
    "VarianceExplained": 0.0401662519
  },
  "c_comp_cor_04": {
    "CumulativeVarianceExplained": 0.4338781757,
    "Mask": "CSF",
    "Method": "aCompCor",
    "Retained": true,
    "SingularValue": 44.8979698604,
    "VarianceExplained": 0.0335971283
  },
  "c_comp_cor_05": {
    "CumulativeVarianceExplained": 0.4612723944,
    "Mask": "CSF",
    "Method": "aCompCor",
    "Retained": true,
    "SingularValue": 40.5419920663,
    "VarianceExplained": 0.0273942187
  },
  "c_comp_cor_06": {
    "CumulativeVarianceExplained": 0.4878934305,
    "Mask": "CSF",
    "Method": "aCompCor",
    "Retained": true,
    "SingularValue": 39.9657623902,
    "VarianceExplained": 0.0266210361
  },
  "c_comp_cor_07": {
    "CumulativeVarianceExplained": 0.5125193546,
    "Mask": "CSF",
    "Method": "aCompCor",
    "Retained": true,
    "SingularValue": 38.4389834136,
    "VarianceExplained": 0.0246259241
  },
  "csf": {
    "Method": "Mean"
  },
  "csf_wm": {
    "Method": "Mean"
  },
  "global_signal": {
    "Method": "Mean"
  },
  "t_comp_cor_00": {
    "CumulativeVarianceExplained": 0.2474528984,
    "Method": "tCompCor",
    "Retained": true,
    "SingularValue": 189.8786120162,
    "VarianceExplained": 0.2474528984
  },
  "t_comp_cor_01": {
    "CumulativeVarianceExplained": 0.4889112986,
    "Method": "tCompCor",
    "Retained": true,
    "SingularValue": 187.5646259527,
    "VarianceExplained": 0.2414584002
  },
  "t_comp_cor_02": {
    "CumulativeVarianceExplained": 0.5497312862,
    "Method": "tCompCor",
    "Retained": true,
    "SingularValue": 94.1353928544,
    "VarianceExplained": 0.0608199876
  },
  "tcompcor": {
    "Method": "Mean"
  },
  "w_comp_cor_00": {
    "CumulativeVarianceExplained": 0.0337000387,
    "Mask": "WM",
    "Method": "aCompCor",
    "Retained": true,
    "SingularValue": 91.1430718615,
    "VarianceExplained": 0.0337000387
  },
  "w_comp_cor_01": {
    "CumulativeVarianceExplained": 0.0602921885,
    "Mask": "WM",
    "Method": "aCompCor",
    "Retained": true,
    "SingularValue": 80.9627379001,
    "VarianceExplained": 0.0265921498
  },
  "w_comp_cor_02": {
    "CumulativeVarianceExplained": 0.0796551292,
    "Mask": "WM",
    "Method": "aCompCor",
    "Retained": true,
    "SingularValue": 69.0866475049,
    "VarianceExplained": 0.0193629406
  },
  "w_comp_cor_03": {
    "CumulativeVarianceExplained": 0.098143189,
    "Mask": "WM",
    "Method": "aCompCor",
    "Retained": true,
    "SingularValue": 67.5078272733,
    "VarianceExplained": 0.0184880598
  },
  "w_comp_cor_04": {
    "CumulativeVarianceExplained": 0.1155244024,
    "Mask": "WM",
    "Method": "aCompCor",
    "Retained": true,
    "SingularValue": 65.4558562234,
    "VarianceExplained": 0.0173812134
  },
  "w_comp_cor_05": {
    "CumulativeVarianceExplained": 0.132008336,
    "Mask": "WM",
    "Method": "aCompCor",
    "Retained": true,
    "SingularValue": 63.7439379311,
    "VarianceExplained": 0.0164839336
  },
  "w_comp_cor_06": {
    "CumulativeVarianceExplained": 0.1479306022,
    "Mask": "WM",
    "Method": "aCompCor",
    "Retained": true,
    "SingularValue": 62.6485325626,
    "VarianceExplained": 0.0159222663
  },
  "w_comp_cor_07": {
    "CumulativeVarianceExplained": 0.1637447064,
    "Mask": "WM",
    "Method": "aCompCor",
    "Retained": true,
    "SingularValue": 62.435379907,
    "VarianceExplained": 0.0158141041
  },
  "w_comp_cor_08": {
    "CumulativeVarianceExplained": 0.1789617729,
    "Mask": "WM",
    "Method": "aCompCor",
    "Retained": true,
    "SingularValue": 61.245464257,
    "VarianceExplained": 0.0152170665
  },
  "w_comp_cor_09": {
    "CumulativeVarianceExplained": 0.1937254845,
    "Mask": "WM",
    "Method": "aCompCor",
    "Retained": true,
    "SingularValue": 60.3262374228,
    "VarianceExplained": 0.0147637116
  },
  "w_comp_cor_10": {
    "CumulativeVarianceExplained": 0.2082197275,
    "Mask": "WM",
    "Method": "aCompCor",
    "Retained": true,
    "SingularValue": 59.7731619759,
    "VarianceExplained": 0.014494243
  },
  "w_comp_cor_11": {
    "CumulativeVarianceExplained": 0.2225534423,
    "Mask": "WM",
    "Method": "aCompCor",
    "Retained": true,
    "SingularValue": 59.4412374633,
    "VarianceExplained": 0.0143337149
  },
  "w_comp_cor_12": {
    "CumulativeVarianceExplained": 0.2367710704,
    "Mask": "WM",
    "Method": "aCompCor",
    "Retained": true,
    "SingularValue": 59.2000448296,
    "VarianceExplained": 0.014217628
  },
  "w_comp_cor_13": {
    "CumulativeVarianceExplained": 0.2506319214,
    "Mask": "WM",
    "Method": "aCompCor",
    "Retained": true,
    "SingularValue": 58.4525430581,
    "VarianceExplained": 0.0138608511
  },
  "w_comp_cor_14": {
    "CumulativeVarianceExplained": 0.264292441,
    "Mask": "WM",
    "Method": "aCompCor",
    "Retained": true,
    "SingularValue": 58.0285969768,
    "VarianceExplained": 0.0136605195
  },
  "w_comp_cor_15": {
    "CumulativeVarianceExplained": 0.2777815914,
    "Mask": "WM",
    "Method": "aCompCor",
    "Retained": true,
    "SingularValue": 57.6634683607,
    "VarianceExplained": 0.0134891504
  },
  "w_comp_cor_16": {
    "CumulativeVarianceExplained": 0.2911639715,
    "Mask": "WM",
    "Method": "aCompCor",
    "Retained": true,
    "SingularValue": 57.4348038235,
    "VarianceExplained": 0.0133823801
  },
  "w_comp_cor_17": {
    "CumulativeVarianceExplained": 0.3043868604,
    "Mask": "WM",
    "Method": "aCompCor",
    "Retained": true,
    "SingularValue": 57.0915241081,
    "VarianceExplained": 0.0132228889
  },
  "w_comp_cor_18": {
    "CumulativeVarianceExplained": 0.3174871939,
    "Mask": "WM",
    "Method": "aCompCor",
    "Retained": true,
    "SingularValue": 56.8263337403,
    "VarianceExplained": 0.0131003335
  },
  "w_comp_cor_19": {
    "CumulativeVarianceExplained": 0.3304235534,
    "Mask": "WM",
    "Method": "aCompCor",
    "Retained": true,
    "SingularValue": 56.4695724697,
    "VarianceExplained": 0.0129363595
  },
  "w_comp_cor_20": {
    "CumulativeVarianceExplained": 0.3431286434,
    "Mask": "WM",
    "Method": "aCompCor",
    "Retained": true,
    "SingularValue": 55.9625291724,
    "VarianceExplained": 0.0127050899
  },
  "w_comp_cor_21": {
    "CumulativeVarianceExplained": 0.3557514173,
    "Mask": "WM",
    "Method": "aCompCor",
    "Retained": true,
    "SingularValue": 55.7809444383,
    "VarianceExplained": 0.0126227739
  },
  "w_comp_cor_22": {
    "CumulativeVarianceExplained": 0.3680503405,
    "Mask": "WM",
    "Method": "aCompCor",
    "Retained": true,
    "SingularValue": 55.0607353388,
    "VarianceExplained": 0.0122989232
  },
  "w_comp_cor_23": {
    "CumulativeVarianceExplained": 0.3802079883,
    "Mask": "WM",
    "Method": "aCompCor",
    "Retained": true,
    "SingularValue": 54.7435857294,
    "VarianceExplained": 0.0121576478
  },
  "w_comp_cor_24": {
    "CumulativeVarianceExplained": 0.3922435226,
    "Mask": "WM",
    "Method": "aCompCor",
    "Retained": true,
    "SingularValue": 54.4679651276,
    "VarianceExplained": 0.0120355344
  },
  "w_comp_cor_25": {
    "CumulativeVarianceExplained": 0.4040824965,
    "Mask": "WM",
    "Method": "aCompCor",
    "Retained": true,
    "SingularValue": 54.0213573561,
    "VarianceExplained": 0.0118389738
  },
  "w_comp_cor_26": {
    "CumulativeVarianceExplained": 0.4157964748,
    "Mask": "WM",
    "Method": "aCompCor",
    "Retained": true,
    "SingularValue": 53.7354227644,
    "VarianceExplained": 0.0117139783
  },
  "w_comp_cor_27": {
    "CumulativeVarianceExplained": 0.4273528861,
    "Mask": "WM",
    "Method": "aCompCor",
    "Retained": true,
    "SingularValue": 53.3727963193,
    "VarianceExplained": 0.0115564113
  },
  "w_comp_cor_28": {
    "CumulativeVarianceExplained": 0.4388587477,
    "Mask": "WM",
    "Method": "aCompCor",
    "Retained": true,
    "SingularValue": 53.2559375273,
    "VarianceExplained": 0.0115058616
  },
  "w_comp_cor_29": {
    "CumulativeVarianceExplained": 0.4503159016,
    "Mask": "WM",
    "Method": "aCompCor",
    "Retained": true,
    "SingularValue": 53.1430938665,
    "VarianceExplained": 0.0114571539
  },
  "w_comp_cor_30": {
    "CumulativeVarianceExplained": 0.4616298428,
    "Mask": "WM",
    "Method": "aCompCor",
    "Retained": true,
    "SingularValue": 52.8099093046,
    "VarianceExplained": 0.0113139413
  },
  "w_comp_cor_31": {
    "CumulativeVarianceExplained": 0.4728226607,
    "Mask": "WM",
    "Method": "aCompCor",
    "Retained": true,
    "SingularValue": 52.5264657278,
    "VarianceExplained": 0.0111928179
  },
  "w_comp_cor_32": {
    "CumulativeVarianceExplained": 0.4839318513,
    "Mask": "WM",
    "Method": "aCompCor",
    "Retained": true,
    "SingularValue": 52.3298717483,
    "VarianceExplained": 0.0111091906
  },
  "w_comp_cor_33": {
    "CumulativeVarianceExplained": 0.4949269748,
    "Mask": "WM",
    "Method": "aCompCor",
    "Retained": true,
    "SingularValue": 52.060522083,
    "VarianceExplained": 0.0109951236
  },
  "w_comp_cor_34": {
    "CumulativeVarianceExplained": 0.5058179635,
    "Mask": "WM",
    "Method": "aCompCor",
    "Retained": true,
    "SingularValue": 51.8134026687,
    "VarianceExplained": 0.0108909886
  },
  "white_matter": {
    "Method": "Mean"
  }
}